invenio_banners/__init__.py
invenio_banners/config.py
invenio_banners/ext.py
invenio_banners/proxies.py
invenio_banners/utils.py
invenio_banners/views.py
invenio_banners/administration/__init__.py
invenio_banners/administration/banners.py
invenio_banners/alembic/3bfaeb3d8eff_change_datetime_types.py
invenio_banners/alembic/5e02314da32e_create_invenio_banners_db_table.py
invenio_banners/alembic/e40d93d99040_create_invenio_banners_branch.py
invenio_banners/records/__init__.py
invenio_banners/records/models.py
invenio_banners/resources/__init__.py
invenio_banners/resources/config.py
invenio_banners/resources/errors.py
invenio_banners/resources/resource.py
invenio_banners/services/__init__.py
invenio_banners/services/config.py
invenio_banners/services/permissions.py
invenio_banners/services/results.py
invenio_banners/services/schemas.py
invenio_banners/services/service.py
invenio_banners/templates/semantic-ui/invenio_banners/banner.html
invenio_banners/translations/messages.pot
invenio_banners/translations/ar/LC_MESSAGES/messages.mo
invenio_banners/translations/ar/LC_MESSAGES/messages.po
invenio_banners/translations/bg/LC_MESSAGES/messages.mo
invenio_banners/translations/bg/LC_MESSAGES/messages.po
invenio_banners/translations/ca/LC_MESSAGES/messages.mo
invenio_banners/translations/ca/LC_MESSAGES/messages.po
invenio_banners/translations/cs/LC_MESSAGES/messages.mo
invenio_banners/translations/cs/LC_MESSAGES/messages.po
invenio_banners/translations/da/LC_MESSAGES/messages.mo
invenio_banners/translations/da/LC_MESSAGES/messages.po
invenio_banners/translations/de/LC_MESSAGES/messages.mo
invenio_banners/translations/de/LC_MESSAGES/messages.po
invenio_banners/translations/el/LC_MESSAGES/messages.mo
invenio_banners/translations/el/LC_MESSAGES/messages.po
invenio_banners/translations/es/LC_MESSAGES/messages.mo
invenio_banners/translations/es/LC_MESSAGES/messages.po
invenio_banners/translations/et/LC_MESSAGES/messages.mo
invenio_banners/translations/et/LC_MESSAGES/messages.po
invenio_banners-6.0.0.dist-info/licenses/AUTHORS.rst
invenio_banners-6.0.0.dist-info/licenses/LICENSE
invenio_banners-6.0.0.dist-info/METADATA
invenio_banners-6.0.0.dist-info/WHEEL
invenio_banners-6.0.0.dist-info/entry_points.txt
invenio_banners-6.0.0.dist-info/top_level.txt
invenio_banners-6.0.0.dist-info/RECORD
