Metadata-Version: 2.4
Name: invenio-banners
Version: 6.0.0
Summary: Invenio-Banners is a module used to create and show banners with useful messages to users.
Home-page: https://github.com/inveniosoftware/invenio-banners
Author: CERN
Author-email: info@inveniosoftware.org
License: MIT
Keywords: Invenio Banners
Platform: any
Classifier: Development Status :: 1 - Planning
Requires-Python: >=3.7
License-File: LICENSE
License-File: AUTHORS.rst
Requires-Dist: invenio-i18n<4.0.0,>=3.0.0
Requires-Dist: invenio-administration<6.0.0,>=5.0.0
Requires-Dist: invenio-records-resources<10.0.0,>=9.0.0
Provides-Extra: tests
Requires-Dist: pytest-black>=0.6.0; extra == "tests"
Requires-Dist: pytest-invenio<5.0.0,>=4.0.0; extra == "tests"
Requires-Dist: jsonresolver>=0.5; extra == "tests"
Requires-Dist: invenio-app<4.0.0,>=3.0.0; extra == "tests"
Requires-Dist: sphinx>=4.5; extra == "tests"
Provides-Extra: opensearch1
Requires-Dist: invenio-search[opensearch1]<4.0.0,>=3.0.0; extra == "opensearch1"
Provides-Extra: opensearch2
Requires-Dist: invenio-search[opensearch2]<4.0.0,>=3.0.0; extra == "opensearch2"
Dynamic: license-file
